dag/__init__.py
dag/dag.py
dag/utils.py
py_ipld_dag-0.1.0.dist-info/DESCRIPTION.rst
py_ipld_dag-0.1.0.dist-info/METADATA
py_ipld_dag-0.1.0.dist-info/RECORD
py_ipld_dag-0.1.0.dist-info/WHEEL
py_ipld_dag-0.1.0.dist-info/metadata.json
py_ipld_dag-0.1.0.dist-info/top_level.txt
