Metadata-Version: 2.0
Name: py-ipld-dag
Version: 0.1.0
Summary: MerkelDAG implementation in Python
Home-page: https://github.com/ipld/py-ipld-dag
Author: Dhruv Baldawa
Author-email: dhruv@dhruvb.com
License: MIT license
Keywords: dag
Platform: UNKNOWN
Classifier: Development Status :: 2 - Pre-Alpha
Classifier: Intended Audience :: Developers
Classifier: License :: OSI Approved :: MIT License
Classifier: Natural Language :: English
Classifier: Programming Language :: Python :: 3
Classifier: Programming Language :: Python :: 3.4
Classifier: Programming Language :: Python :: 3.5
Classifier: Programming Language :: Python :: 3.6
Requires-Dist: morphys (==1.0)
Requires-Dist: pymultihash (==0.8.2)
Requires-Dist: pyrsistent (==0.13.0)
